eevolve/__init__.py
eevolve/agent.py
eevolve/board.py
eevolve/brain.py
eevolve/constants.py
eevolve/eemath.py
eevolve/game.py
eevolve/generator.py
eevolve/loader.py
eevolve/task.py
eevolve-0.0.9.dist-info/LICENSE
eevolve-0.0.9.dist-info/METADATA
eevolve-0.0.9.dist-info/WHEEL
eevolve-0.0.9.dist-info/top_level.txt
eevolve-0.0.9.dist-info/RECORD
